py_currency_fetcher/__init__.py
py_currency_fetcher/currency.py
py_currency_fetcher/get_exchange_rate.py
tests/__init__.py
tests/test_exchange_rate.py
py_currency_fetcher-0.9.dist-info/METADATA
py_currency_fetcher-0.9.dist-info/WHEEL
py_currency_fetcher-0.9.dist-info/top_level.txt
py_currency_fetcher-0.9.dist-info/RECORD
