Metadata-Version: 2.1
Name: py_currency_fetcher
Version: 0.9
Summary: A simple package to fetch py_currency_fetcher by country code
Author: Volodymyr Lekhman
Author-email: volodya.l@yahoo.com
Requires-Dist: pycountry >=20.7.3
